{"_type":"export","__export_format":4,"__export_date":"2021-11-23T21:19:18.744Z","__export_source":"insomnia.desktop.app:v2021.6.0","resources":[{"_id":"req_663bb384968a4fa6bc07e173902e30e5","parentId":"fld_d17da766a36e4877b56bcf235f38182d","modified":1637683559112,"created":1636984132186,"url":"{{ _.baseUrl }}/afternoon/air-diffuser/1","name":"Get specific air diffuser","description":"","method":"GET","body":{},"parameters":[],"headers":[],"authentication":{},"metaSortKey":-1636984132186,"isPrivate":false,"settingStoreCookies":true,"settingSendCookies":true,"settingDisableRenderRequestBody":false,"settingEncodeUrl":true,"settingRebuildPath":true,"settingFollowRedirects":"global","_type":"request"},{"_id":"fld_d17da766a36e4877b56bcf235f38182d","parentId":"wrk_7d57848f6bc94730a1d199cc63a4156f","modified":1636979467236,"created":1636978817341,"name":"Afternoon","description":"","environment":{},"environmentPropertyOrder":null,"metaSortKey":-1636965323091,"_type":"request_group"},{"_id":"wrk_7d57848f6bc94730a1d199cc63a4156f","parentId":null,"modified":1636916839787,"created":1636916839787,"name":"ES Trab Final","description":"","scope":"collection","_type":"workspace"},{"_id":"req_e1de8d0f760e48d9ad6cd5696233ce9f","parentId":"fld_d17da766a36e4877b56bcf235f38182d","modified":1636984151278,"created":1636984126476,"url":"{{ _.baseUrl }}/afternoon/air-diffuser","name":"Get all air diffusers","description":"","method":"GET","body":{},"parameters":[],"headers":[],"authentication":{},"metaSortKey":-1636984126476,"isPrivate":false,"settingStoreCookies":true,"settingSendCookies":true,"settingDisableRenderRequestBody":false,"settingEncodeUrl":true,"settingRebuildPath":true,"settingFollowRedirects":"global","_type":"request"},{"_id":"req_c44bbc4069aa445a88344924208155c4","parentId":"fld_d17da766a36e4877b56bcf235f38182d","modified":1637698384069,"created":1636984185012,"url":"{{ _.baseUrl }}/afternoon/air-diffuser/start","name":"Start diffusing","description":"","method":"POST","body":{"mimeType":"application/json","text":"{\n\t\"airDiffuserId\": 1,\n\t\"slot\": 1\n}"},"parameters":[],"headers":[{"name":"Content-Type","value":"application/json","id":"pair_f9a8ed7939de41b3a6e45624b2eb5e7e"}],"authentication":{},"metaSortKey":-1636981794132,"isPrivate":false,"settingStoreCookies":true,"settingSendCookies":true,"settingDisableRenderRequestBody":false,"settingEncodeUrl":true,"settingRebuildPath":true,"settingFollowRedirects":"global","_type":"request"},{"_id":"req_a507de35393d47448e2e2b3572c32ac6","parentId":"fld_d17da766a36e4877b56bcf235f38182d","modified":1637586049384,"created":1636984694234,"url":"{{ _.baseUrl }}/afternoon/air-diffuser/schedule","name":"Schedule diffusing","description":"","method":"POST","body":{"mimeType":"application/json","text":"{\n\t\"airDiffuserId\": 1,\n\t\"slot\": 1,\n\t\"startTimestamp\": 1636985080610\n}"},"parameters":[],"headers":[{"name":"Content-Type","value":"application/json","id":"pair_f9a8ed7939de41b3a6e45624b2eb5e7e"}],"authentication":{},"metaSortKey":-1636980627960,"isPrivate":false,"settingStoreCookies":true,"settingSendCookies":true,"settingDisableRenderRequestBody":false,"settingEncodeUrl":true,"settingRebuildPath":true,"settingFollowRedirects":"global","_type":"request"},{"_id":"req_f751d68ea6a44de0aa18fa7f98a80978","parentId":"fld_d17da766a36e4877b56bcf235f38182d","modified":1636979461788,"created":1636979461788,"url":"","name":"Schedule cleaning","description":"","method":"GET","body":{},"parameters":[],"headers":[],"authentication":{},"metaSortKey":-1636979461788,"isPrivate":false,"settingStoreCookies":true,"settingSendCookies":true,"settingDisableRenderRequestBody":false,"settingEncodeUrl":true,"settingRebuildPath":true,"settingFollowRedirects":"global","_type":"request"},{"_id":"req_5c6e716792d5487087bf8a0d22b0aee8","parentId":"fld_d17da766a36e4877b56bcf235f38182d","modified":1637591347672,"created":1636978859695,"url":"{{ _.baseUrl }}/afternoon/robot/start","name":"Start cleaning","description":"","method":"POST","body":{"mimeType":"application/json","text":"{\n\t\"robotId\": 1\n}"},"parameters":[],"headers":[{"name":"Content-Type","value":"application/json","id":"pair_f9a8ed7939de41b3a6e45624b2eb5e7e"}],"authentication":{},"metaSortKey":-1636978847465,"isPrivate":false,"settingStoreCookies":true,"settingSendCookies":true,"settingDisableRenderRequestBody":false,"settingEncodeUrl":true,"settingRebuildPath":true,"settingFollowRedirects":"global","_type":"request"},{"_id":"req_c69baf0a8df043c38b7c3955f7f2904d","parentId":"fld_d17da766a36e4877b56bcf235f38182d","modified":1636984143194,"created":1636978904406,"url":"{{ _.baseUrl }}/afternoon/robot/schedule","name":"Schedule cleaning","description":"","method":"POST","body":{"mimeType":"application/json","text":"{\n\t\"robotId\": 2,\n\t\"startTimestamp\": 1636979661963\n}"},"parameters":[],"headers":[{"name":"Content-Type","value":"application/json","id":"pair_3b184ee3a13f4ae9a22d76e1d4ce3664"}],"authentication":{},"metaSortKey":-1636978847440,"isPrivate":false,"settingStoreCookies":true,"settingSendCookies":true,"settingDisableRenderRequestBody":false,"settingEncodeUrl":true,"settingRebuildPath":true,"settingFollowRedirects":"global","_type":"request"},{"_id":"req_7809eee3ed3547d7ae83980abde48283","parentId":"fld_d17da766a36e4877b56bcf235f38182d","modified":1636979024072,"created":1636978847415,"url":"{{ _.baseUrl }}/afternoon/robot/1","name":"Get specific robot","description":"","method":"GET","body":{},"parameters":[],"headers":[],"authentication":{},"metaSortKey":-1636978847415,"isPrivate":false,"settingStoreCookies":true,"settingSendCookies":true,"settingDisableRenderRequestBody":false,"settingEncodeUrl":true,"settingRebuildPath":true,"settingFollowRedirects":"global","_type":"request"},{"_id":"req_3b849a40b1804ea5a5cb595c134ca102","parentId":"fld_d17da766a36e4877b56bcf235f38182d","modified":1636978839851,"created":1636978819956,"url":"{{ _.baseUrl }}/afternoon/robot","name":"Get all robots","description":"","method":"GET","body":{},"parameters":[],"headers":[],"authentication":{},"metaSortKey":-1636978819956,"isPrivate":false,"settingStoreCookies":true,"settingSendCookies":true,"settingDisableRenderRequestBody":false,"settingEncodeUrl":true,"settingRebuildPath":true,"settingFollowRedirects":"global","_type":"request"},{"_id":"req_71a3ac338c054bb69bdc80d06ffa8ece","parentId":"fld_ff83f24cf16a45f2926901a94e0a0456","modified":1637683714464,"created":1636989982532,"url":"{{ _.baseUrl }}/night/speaker/stop","name":"Stop sound on speaker","description":"","method":"POST","body":{"mimeType":"application/json","text":"{\n\t\"speakerId\": 1\n}"},"parameters":[],"headers":[{"name":"Content-Type","value":"application/json","id":"pair_bb417f5a893e4e199d99f4e29b7bc544"}],"authentication":{},"metaSortKey":-1636989982532,"isPrivate":false,"settingStoreCookies":true,"settingSendCookies":true,"settingDisableRenderRequestBody":false,"settingEncodeUrl":true,"settingRebuildPath":true,"settingFollowRedirects":"global","_type":"request"},{"_id":"fld_ff83f24cf16a45f2926901a94e0a0456","parentId":"wrk_7d57848f6bc94730a1d199cc63a4156f","modified":1636924840341,"created":1636924840341,"name":"Night","description":"","environment":{},"environmentPropertyOrder":null,"metaSortKey":-1636924840341,"_type":"request_group"},{"_id":"req_d5baadd2e08e4146b9fe37b00ef693ca","parentId":"fld_ff83f24cf16a45f2926901a94e0a0456","modified":1637701397169,"created":1636989976347,"url":"{{ _.baseUrl }}/night/speaker/play","name":"Play sound on speaker","description":"","method":"POST","body":{"mimeType":"application/json","text":"{\n\t\"speakerId\": 1\n}"},"parameters":[],"headers":[{"name":"Content-Type","value":"application/json","id":"pair_c29922736f57440bbe1db10e99450abf"}],"authentication":{},"metaSortKey":-1636989976347,"isPrivate":false,"settingStoreCookies":true,"settingSendCookies":true,"settingDisableRenderRequestBody":false,"settingEncodeUrl":true,"settingRebuildPath":true,"settingFollowRedirects":"global","_type":"request"},{"_id":"req_602a2402cf0c4b7685518962364c5771","parentId":"fld_ff83f24cf16a45f2926901a94e0a0456","modified":1636990020291,"created":1636989971415,"url":"{{ _.baseUrl }}/night/speaker/1","name":"Get specific speaker","description":"","method":"GET","body":{},"parameters":[],"headers":[],"authentication":{},"metaSortKey":-1636989971415,"isPrivate":false,"settingStoreCookies":true,"settingSendCookies":true,"settingDisableRenderRequestBody":false,"settingEncodeUrl":true,"settingRebuildPath":true,"settingFollowRedirects":"global","_type":"request"},{"_id":"req_32124dfd441f4d64a44f0e91ab18fffa","parentId":"fld_ff83f24cf16a45f2926901a94e0a0456","modified":1636990003298,"created":1636989966897,"url":"{{ _.baseUrl }}/night/speaker","name":"Get all speakers","description":"","method":"GET","body":{},"parameters":[],"headers":[],"authentication":{},"metaSortKey":-1636989966897,"isPrivate":false,"settingStoreCookies":true,"settingSendCookies":true,"settingDisableRenderRequestBody":false,"settingEncodeUrl":true,"settingRebuildPath":true,"settingFollowRedirects":"global","_type":"request"},{"_id":"req_baf5536cfa5c4d93bb2eaa989d61e2e6","parentId":"fld_ff83f24cf16a45f2926901a94e0a0456","modified":1636924847294,"created":1636919195504,"url":"{{ _.baseUrl }}/night/mattress","name":"Get all mattresses","description":"","method":"GET","body":{},"parameters":[],"headers":[],"authentication":{},"metaSortKey":-1636919480698,"isPrivate":false,"settingStoreCookies":true,"settingSendCookies":true,"settingDisableRenderRequestBody":false,"settingEncodeUrl":true,"settingRebuildPath":true,"settingFollowRedirects":"global","_type":"request"},{"_id":"req_0a3c9f73c9a9439baca7a836d63f8b45","parentId":"fld_ff83f24cf16a45f2926901a94e0a0456","modified":1637701414823,"created":1636919601730,"url":"{{ _.baseUrl }}/night/mattress-temperature","name":"Set mattress temp","description":"","method":"PATCH","body":{"mimeType":"application/json","text":"{\n\t\"mattressId\":1,\n\t\"targetTemperature\": 10\n}"},"parameters":[],"headers":[{"name":"Content-Type","value":"application/json","id":"pair_60a86e069ae14f81863862345fbb6ea6"}],"authentication":{},"metaSortKey":-1636919480648,"isPrivate":false,"settingStoreCookies":true,"settingSendCookies":true,"settingDisableRenderRequestBody":false,"settingEncodeUrl":true,"settingRebuildPath":true,"settingFollowRedirects":"global","_type":"request"},{"_id":"req_528f81a6e5ac48baa771336bb9b70da5","parentId":"fld_ff83f24cf16a45f2926901a94e0a0456","modified":1636988371688,"created":1636919480598,"url":"{{ _.baseUrl }}/night/mattress/5","name":"Get specific mattress","description":"","method":"GET","body":{},"parameters":[],"headers":[],"authentication":{},"metaSortKey":-1636919480598,"isPrivate":false,"settingStoreCookies":true,"settingSendCookies":true,"settingDisableRenderRequestBody":false,"settingEncodeUrl":true,"settingRebuildPath":true,"settingFollowRedirects":"global","_type":"request"},{"_id":"req_8cbb296b5214493abf4898e4d8e89639","parentId":"fld_7757662f10dc43e88ed64d84b89fe126","modified":1636924806031,"created":1636923506924,"url":"{{ _.baseUrl }}/morning/coffee-machine","name":"Get all coffee machines","description":"","method":"GET","body":{},"parameters":[],"headers":[],"authentication":{},"metaSortKey":-1636924184571,"isPrivate":false,"settingStoreCookies":true,"settingSendCookies":true,"settingDisableRenderRequestBody":false,"settingEncodeUrl":true,"settingRebuildPath":true,"settingFollowRedirects":"global","_type":"request"},{"_id":"fld_7757662f10dc43e88ed64d84b89fe126","parentId":"wrk_7d57848f6bc94730a1d199cc63a4156f","modified":1636924793381,"created":1636924793381,"name":"Morning","description":"","environment":{},"environmentPropertyOrder":null,"metaSortKey":-1636924793381,"_type":"request_group"},{"_id":"req_8a516318f6eb4d7ea257606aea79618f","parentId":"fld_7757662f10dc43e88ed64d84b89fe126","modified":1637701371849,"created":1636923558789,"url":"{{ _.baseUrl }}/morning/coffee-machine/1","name":"Get coffee machine data","description":"","method":"GET","body":{},"parameters":[],"headers":[],"authentication":{},"metaSortKey":-1636924184521,"isPrivate":false,"settingStoreCookies":true,"settingSendCookies":true,"settingDisableRenderRequestBody":false,"settingEncodeUrl":true,"settingRebuildPath":true,"settingFollowRedirects":"global","_type":"request"},{"_id":"req_e86e8b85e738433ea5eb7f32cc578683","parentId":"fld_7757662f10dc43e88ed64d84b89fe126","modified":1637701383342,"created":1636923575461,"url":"{{ _.baseUrl }}/morning/coffee-machine/make","name":"Make coffee","description":"","method":"POST","body":{"mimeType":"application/json","text":"{\n\t\"coffeeMachineId\": 1,\n\t\"slot\":2\n}"},"parameters":[],"headers":[{"name":"Content-Type","value":"application/json","id":"pair_44a35aed8bac45b2956263e39b87fa63"}],"authentication":{},"metaSortKey":-1636924184471,"isPrivate":false,"settingStoreCookies":true,"settingSendCookies":true,"settingDisableRenderRequestBody":false,"settingEncodeUrl":true,"settingRebuildPath":true,"settingFollowRedirects":"global","_type":"request"},{"_id":"req_a3e23051f070452c950fc5b5cd69794d","parentId":"fld_7757662f10dc43e88ed64d84b89fe126","modified":1636977059964,"created":1636916854214,"url":"{{ _.baseUrl }}/morning/courtain","name":"Get all courtains","description":"","method":"GET","body":{},"parameters":[],"headers":[],"authentication":{},"metaSortKey":-1636924184446,"isPrivate":false,"settingStoreCookies":true,"settingSendCookies":true,"settingDisableRenderRequestBody":false,"settingEncodeUrl":true,"settingRebuildPath":true,"settingFollowRedirects":"global","_type":"request"},{"_id":"req_b1b7cd2caf044be3a9eca569811d2621","parentId":"fld_7757662f10dc43e88ed64d84b89fe126","modified":1636977123259,"created":1636977090088,"url":"{{ _.baseUrl }}/morning/courtain/2","name":"Get specific courtain","description":"","method":"GET","body":{},"parameters":[],"headers":[],"authentication":{},"metaSortKey":-1636924184439.75,"isPrivate":false,"settingStoreCookies":true,"settingSendCookies":true,"settingDisableRenderRequestBody":false,"settingEncodeUrl":true,"settingRebuildPath":true,"settingFollowRedirects":"global","_type":"request"},{"_id":"req_6d533f2a0bae492dbffe4dd1dfdf83cd","parentId":"fld_7757662f10dc43e88ed64d84b89fe126","modified":1636977141615,"created":1636975776926,"url":"{{ _.baseUrl }}/morning/courtain/schedule","name":"Schedule courtain","description":"","method":"POST","body":{"mimeType":"application/json","text":"{\n\t\"courtainId\": 1,\n\t\"courtainState\": \"OPENED\",\n\t\"courtainSpeed\": 9999,\n\t\"startTimestamp\": 1636977159949\n}"},"parameters":[],"headers":[{"name":"Content-Type","value":"application/json","id":"pair_e610f064b8e5446cb2e7d9b8a98fd59a"}],"authentication":{},"metaSortKey":-1636924184433.5,"isPrivate":false,"settingStoreCookies":true,"settingSendCookies":true,"settingDisableRenderRequestBody":false,"settingEncodeUrl":true,"settingRebuildPath":true,"settingFollowRedirects":"global","_type":"request"},{"_id":"req_6578695271604ca48c9ca5076d793d6b","parentId":"fld_7757662f10dc43e88ed64d84b89fe126","modified":1637699341291,"created":1636923852083,"url":"{{ _.baseUrl }}/morning/coffee-machine/schedule","name":"Schedule make coffee","description":"","method":"POST","body":{"mimeType":"application/json","text":"{\n\t\"coffeeMachineId\": 1,\n\t\"slot\": 1,\n\t\"startTimestamp\": 1637699345014\n}"},"parameters":[],"headers":[{"name":"Content-Type","value":"application/json","id":"pair_2302a4c02fe645b58c6c419993b82ceb"}],"authentication":{},"metaSortKey":-1636924184421,"isPrivate":false,"settingStoreCookies":true,"settingSendCookies":true,"settingDisableRenderRequestBody":false,"settingEncodeUrl":true,"settingRebuildPath":true,"settingFollowRedirects":"global","_type":"request"},{"_id":"req_d22c3bc238a8453ba917b2d05c4e78ee","parentId":"fld_7757662f10dc43e88ed64d84b89fe126","modified":1637591327399,"created":1636917900474,"url":"{{ _.baseUrl }}/morning/courtain-speed","name":"Set courtain speed","description":"","method":"PATCH","body":{"mimeType":"application/json","text":"{\n\t\"courtainId\": 1,\n\t\"courtainSpeed\": 10.1\n}"},"parameters":[],"headers":[{"name":"Content-Type","value":"application/json","id":"pair_b92163613f6b4fb48e3ff64ecad761c9"}],"authentication":{},"metaSortKey":-1636924184371,"isPrivate":false,"settingStoreCookies":true,"settingSendCookies":true,"settingDisableRenderRequestBody":false,"settingEncodeUrl":true,"settingRebuildPath":true,"settingFollowRedirects":"global","_type":"request"},{"_id":"req_cc35416b8adb48c8853d60c875984f9d","parentId":"fld_7757662f10dc43e88ed64d84b89fe126","modified":1637591331889,"created":1636917001847,"url":"{{ _.baseUrl }}/morning/courtain-state","name":"Set courtain state","description":"","method":"PATCH","body":{"mimeType":"application/json","text":"{\n\t\"courtainId\": 1,\n\t\"courtainState\": \"CLOSED\"\n}"},"parameters":[],"headers":[{"name":"Content-Type","value":"application/json","id":"pair_20ecda6fef3a4bf8a10c41d17e801aed"}],"authentication":{},"metaSortKey":-1636924184321,"isPrivate":false,"settingStoreCookies":true,"settingSendCookies":true,"settingDisableRenderRequestBody":false,"settingEncodeUrl":true,"settingRebuildPath":true,"settingFollowRedirects":"global","_type":"request"},{"_id":"env_056a6bb8d513735af7456af8d6087eab949e7cf1","parentId":"wrk_7d57848f6bc94730a1d199cc63a4156f","modified":1636916905498,"created":1636916839797,"name":"Base Environment","data":{"BASE_URL":"http://localhost/3000/"},"dataPropertyOrder":{"&":["BASE_URL"]},"color":null,"isPrivate":false,"metaSortKey":1636916839797,"_type":"environment"},{"_id":"jar_056a6bb8d513735af7456af8d6087eab949e7cf1","parentId":"wrk_7d57848f6bc94730a1d199cc63a4156f","modified":1636916839799,"created":1636916839799,"name":"Default Jar","cookies":[],"_type":"cookie_jar"},{"_id":"spc_f14e51f02ab74985ae926ba456cfd904","parentId":"wrk_7d57848f6bc94730a1d199cc63a4156f","modified":1636916839791,"created":1636916839791,"fileName":"ES Trab Final","contents":"","contentType":"yaml","_type":"api_spec"},{"_id":"env_9d78f3bd4d8e4fc69b278417765bf36b","parentId":"env_056a6bb8d513735af7456af8d6087eab949e7cf1","modified":1636916968321,"created":1636916907055,"name":"New Environment","data":{"baseUrl":"http://localhost:3000"},"dataPropertyOrder":{"&":["baseUrl"]},"color":null,"isPrivate":false,"metaSortKey":1636916907056,"_type":"environment"}]}